sparrowTools/__init__.py
sparrowTools/error.py
sparrowTools/data_transform/__init__.py
sparrowTools/data_transform/to_class.py
sparrowTools/digital_to_chinese/__init__.py
sparrowTools/digital_to_chinese/digital_to_chinese.py
sparrowTools/string_split/__init__.py
sparrowTools/string_split/string_split.py
sparrowTools/system_transform/__init__.py
sparrowTools/system_transform/system_and_char.py
sparrowTools/system_transform/system_and_string.py
sparrowTools/system_transform/system_to_new_system.py
sparrowTools-0.1.dist-info/METADATA
sparrowTools-0.1.dist-info/WHEEL
sparrowTools-0.1.dist-info/top_level.txt
sparrowTools-0.1.dist-info/RECORD
